solr_manager/__init__.py
solr_manager/client.py
solr_manager/exception.py
solr_manager/generated/__init__.py
solr_manager/generated/handler/__init__.py
solr_manager/generated/handler/admin/__init__.py
solr_manager/generated/handler/admin/api/__init__.py
solr_manager/generated/handler/admin/api/update_api.py
solr_manager/handler.py
solr_manager/parameters.py
solr_manager/response.py
solr_manager/stub.py
solr_manager/utils.py
solr_manager-0.1.0.dist-info/LICENSE
solr_manager-0.1.0.dist-info/METADATA
solr_manager-0.1.0.dist-info/WHEEL
solr_manager-0.1.0.dist-info/RECORD
