Metadata-Version: 2.1
Name: solr-manager
Version: 0.1.0
Summary: 
Author: Giancarlo Rocha
Author-email: giancarloiff@gmail.com
Requires-Python: >=3.11,<4.0
Classifier: Programming Language :: Python :: 3
Classifier: Programming Language :: Python :: 3.11
Requires-Dist: pyhumps (>=3.8.0,<4.0.0)
Requires-Dist: requests (>=2.31.0,<3.0.0)
